{"name":"jquery.inject","body":"jquery.inject is a plugin for avoiding ugly, unreadable  HTML DOM objecect injections\r\n\r\nThe old way:\r\n\r\n````javascript\r\n$('body').append('<div id=\"header\" class=\"wrapped\"></div>');`\r\n````\r\n\r\nThe new way:\r\n\r\n````javascript\r\nvar body = $('body');\r\nbody.inject('div#header.wrapped');\r\n````\r\n\r\nYou can even pass in an array\r\n````javascript\r\nvar body = $('body');\r\nbody.inject(['div#header.wrapped','div#main.wrapped']);\r\n````\r\n\r\nInjections automatically create a tree that can be easily traverse. Object names are dynamically created from the first given attribute ('id' or 'class').\r\n````javascript\r\nvar body = $('body');\r\nbody.inject(['div#header.wrapped','div#main.wrapped']);\r\n//Automatically creates body.header and body.main\r\nbody.header.inject('span.title');\r\nbody.main.inject('div.left');\r\nbody.main.inject('div.right');\r\n````\r\n","tagline":"A jQuery plugin that allows you to easily inject HTML DOM objects without bulky selectors and annoying append()s.","google":"UA-32742952-1","note":"Don't delete this file! It's used internally to help with page regeneration."}
